shapes_area/__init__.py
shapes_area/shapes_area.py
square_shapez-0.0.1.dist-info/METADATA
square_shapez-0.0.1.dist-info/WHEEL
square_shapez-0.0.1.dist-info/top_level.txt
square_shapez-0.0.1.dist-info/RECORD
