Metadata-Version: 2.1
Name: square_shapez
Version: 0.0.1
Summary: This is module to calculate shapes area.
Home-page: https://github.com/Similization/ShapeAreaLib
Author: reducter
Author-email: example@gmail.com
License: UNKNOWN
Project-URL: GitHub, https://github.com/Similization/ShapeAreaLib
Keywords: shapes area
Platform: UNKNOWN
Classifier: Programming Language :: Python :: 3.11
Classifier: License :: OSI Approved :: MIT License
Classifier: Operating System :: OS Independent
Requires-Python: >=3.6
